envist/__init__.py
envist/config.py
envist/logger.py
envist/core/__init__.py
envist/core/exceptions.py
envist/core/parser.py
envist/utils/__init__.py
envist/utils/file_handler.py
envist/utils/type_casters.py
envist/validators/__init__.py
envist/validators/env_validator.py
envist-0.1.3.dist-info/METADATA
envist-0.1.3.dist-info/WHEEL
envist-0.1.3.dist-info/licenses/LICENSE
envist-0.1.3.dist-info/RECORD
