Metadata-Version: 2.4
Name: envist
Version: 0.1.3
Summary: A simple .env file parser with types for Python
Project-URL: Homepage, https://github.com/Almas-Ali/envist
Project-URL: Documentation, https://github.com/Almas-Ali/envist#readme
Project-URL: Repository, https://github.com/Almas-Ali/envist
Project-URL: Bug Tracker, https://github.com/Almas-Ali/envist/issues
Author-email: "Md. Almas Ali" <almaspr3@gmail.com>
License: MIT License
License-File: LICENSE
Classifier: Development Status :: 4 - Beta
Classifier: Intended Audience :: Developers
Classifier: License :: OSI Approved :: MIT License
Classifier: Operating System :: OS Independent
Classifier: Programming Language :: Python :: 3
Classifier: Programming Language :: Python :: 3.10
Classifier: Programming Language :: Python :: 3.11
Classifier: Programming Language :: Python :: 3.12
Classifier: Programming Language :: Python :: 3.13
Classifier: Programming Language :: Python :: 3.14
Classifier: Topic :: Software Development :: Libraries :: Python Modules
Classifier: Topic :: Utilities
Requires-Python: <4.0,>=3.10
Provides-Extra: dev
Requires-Dist: coverage>=7.0.0; extra == 'dev'
Requires-Dist: pytest-cov>=4.0.0; extra == 'dev'
Requires-Dist: pytest-mock>=3.10.0; extra == 'dev'
Requires-Dist: pytest>=7.0.0; extra == 'dev'
